{
  "$schema": "https://developer.microsoft.com/json-schemas/fabric/item/report/definition/bookmark/2.1.0/schema.json",
  "displayName": "HF VA",
  "name": "f0ecbbe0120b1383931b",
  "options": {
    "applyOnlyToTargetVisuals": true,
    "targetVisualNames": [
      "9691909fa47ae10dc2d9",
      "2937f73de1287b220a93",
      "c6271b1ee72a7262bc61",
      "ce6049150030e4926b02",
      "dc9fb361e37640021d18",
      "35064b3aaed540958de2",
      "d92418f3d6ba070c09ac",
      "fb3c27dd36306a8b25a4",
      "469ab4e5bbc2c210b89b",
      "8e6b56182aaa0ca17243",
      "ec98c2462757355e04da",
      "ec080d215cc6e0bd5b06",
      "59500c8451eeed88a37e",
      "01c2f3712d39b783bb77",
      "9a8f590f15430c64442c",
      "b5defe4ce068844ad106",
      "95895f54a692e600d350",
      "554423c0be108863eba1",
      "346b79f147d6e6015bd1",
      "ac5d04e864192bb00150",
      "0416dc2514d1a1c3e2d8",
      "8eadd82d15bb835c2a5d"
    ],
    "suppressData": true
  },
  "explorationState": {
    "version": "1.3",
    "activeSection": "f0abaee3e3cd389c5170",
    "filters": {
      "byExpr": [
        {
          "name": "3a6001480ccae0666a23",
          "type": "Advanced",
          "filter": {
            "Version": 2,
            "From": [
              {
                "Name": "p",
                "Entity": "public visits",
                "Type": 0
              }
            ],
            "Where": [
              {
                "Condition": {
                  "Comparison": {
                    "ComparisonKind": 2,
                    "Left": {
                      "Column": {
                        "Expression": {
                          "SourceRef": {
                            "Source": "p"
                          }
                        },
                        "Property": "Visit Date"
                      }
                    },
                    "Right": {
                      "DateSpan": {
                        "Expression": {
                          "Literal": {
                            "Value": "datetime'2026-01-01T00:00:00'"
                          }
                        },
                        "TimeUnit": 5
                      }
                    }
                  }
                }
              }
            ]
          },
          "expression": {
            "Column": {
              "Expression": {
                "SourceRef": {
                  "Entity": "public visits"
                }
              },
              "Property": "Visit Date"
            }
          },
          "howCreated": 1
        }
      ]
    },
    "sections": {
      "f0abaee3e3cd389c5170": {
        "filters": {
          "byExpr": [
            {
              "name": "ee50d8671026d15c5e47",
              "type": "Categorical",
              "filter": {
                "Version": 2,
                "From": [
                  {
                    "Name": "p",
                    "Entity": "public customers",
                    "Type": 0
                  }
                ],
                "Where": [
                  {
                    "Condition": {
                      "Not": {
                        "Expression": {
                          "In": {
                            "Expressions": [
                              {
                                "Column": {
                                  "Expression": {
                                    "SourceRef": {
                                      "Source": "p"
                                    }
                                  },
                                  "Property": "Sector"
                                }
                              }
                            ],
                            "Values": [
                              [
                                {
                                  "Literal": {
                                    "Value": "'OFFICE'"
                                  }
                                }
                              ]
                            ]
                          }
                        }
                      }
                    }
                  }
                ]
              },
              "expression": {
                "Column": {
                  "Expression": {
                    "SourceRef": {
                      "Entity": "public customers"
                    }
                  },
                  "Property": "Sector"
                }
              },
              "howCreated": 1
            },
            {
              "name": "8bcc70e890938baac7c8",
              "type": "Categorical",
              "filter": {
                "Version": 2,
                "From": [
                  {
                    "Name": "p",
                    "Entity": "public objectives",
                    "Type": 0
                  }
                ],
                "Where": [
                  {
                    "Condition": {
                      "Not": {
                        "Expression": {
                          "In": {
                            "Expressions": [
                              {
                                "Column": {
                                  "Expression": {
                                    "SourceRef": {
                                      "Source": "p"
                                    }
                                  },
                                  "Property": "Objective Category"
                                }
                              }
                            ],
                            "Values": [
                              [
                                {
                                  "Literal": {
                                    "Value": "'06. Office Work'"
                                  }
                                }
                              ],
                              [
                                {
                                  "Literal": {
                                    "Value": "'C. Office Work'"
                                  }
                                }
                              ]
                            ]
                          }
                        }
                      }
                    }
                  }
                ]
              },
              "expression": {
                "Column": {
                  "Expression": {
                    "SourceRef": {
                      "Entity": "public objectives"
                    }
                  },
                  "Property": "Objective Category"
                }
              },
              "howCreated": 1
            }
          ]
        },
        "visualContainers": {
          "2937f73de1287b220a93": {
            "filters": {
              "byExpr": [
                {
                  "name": "58536856d0374a5c0e20",
                  "type": "Advanced",
                  "expression": {
                    "Aggregation": {
                      "Expression": {
                        "Column": {
                          "Expression": {
                            "SourceRef": {
                              "Entity": "RefreshStamp"
                            }
                          },
                          "Property": "local_ast"
                        }
                      },
                      "Function": 3
                    }
                  },
                  "howCreated": 0
                }
              ]
            },
            "singleVisual": {
              "visualType": "card",
              "objects": {}
            }
          },
          "dc9fb361e37640021d18": {
            "filters": {
              "byExpr": [
                {
                  "name": "f10e3800d2017039dc90",
                  "type": "Advanced",
                  "expression": {
                    "Aggregation": {
                      "Expression": {
                        "Column": {
                          "Expression": {
                            "SourceRef": {
                              "Entity": "RefreshStamp"
                            }
                          },
                          "Property": "Msg"
                        }
                      },
                      "Function": 3
                    }
                  },
                  "howCreated": 0
                }
              ]
            },
            "singleVisual": {
              "visualType": "card",
              "objects": {}
            }
          },
          "5c87ec14878a34455db7": {
            "filters": {
              "byExpr": [
                {
                  "name": "29948e97ba88058b0034",
                  "type": "Categorical",
                  "filter": {
                    "Version": 2,
                    "From": [
                      {
                        "Name": "p",
                        "Entity": "public business_units",
                        "Type": 0
                      }
                    ],
                    "Where": [
                      {
                        "Condition": {
                          "Not": {
                            "Expression": {
                              "In": {
                                "Expressions": [
                                  {
                                    "Column": {
                                      "Expression": {
                                        "SourceRef": {
                                          "Source": "p"
                                        }
                                      },
                                      "Property": "Business Unit"
                                    }
                                  }
                                ],
                                "Values": [
                                  [
                                    {
                                      "Literal": {
                                        "Value": "null"
                                      }
                                    }
                                  ],
                                  [
                                    {
                                      "Literal": {
                                        "Value": "'OTHERS'"
                                      }
                                    }
                                  ]
                                ]
                              }
                            }
                          }
                        }
                      }
                    ]
                  },
                  "expression": {
                    "Column": {
                      "Expression": {
                        "SourceRef": {
                          "Entity": "public business_units"
                        }
                      },
                      "Property": "Business Unit"
                    }
                  },
                  "howCreated": 1
                },
                {
                  "name": "dd61457e03270c350072",
                  "type": "Advanced",
                  "expression": {
                    "Column": {
                      "Expression": {
                        "SourceRef": {
                          "Entity": "public visits"
                        }
                      },
                      "Property": "Visit Hour"
                    }
                  },
                  "howCreated": 0
                },
                {
                  "name": "404b36f2245b600e2eee",
                  "type": "Advanced",
                  "expression": {
                    "Aggregation": {
                      "Expression": {
                        "Column": {
                          "Expression": {
                            "SourceRef": {
                              "Entity": "public visits"
                            }
                          },
                          "Property": "Visit #"
                        }
                      },
                      "Function": 5
                    }
                  },
                  "howCreated": 0
                },
                {
                  "name": "638a74c1c316d10d319c",
                  "type": "Categorical",
                  "expression": {
                    "Column": {
                      "Expression": {
                        "SourceRef": {
                          "Entity": "public business_units"
                        }
                      },
                      "Property": "Business Unit Mask"
                    }
                  },
                  "howCreated": 0
                }
              ]
            },
            "singleVisual": {
              "visualType": "lineChart",
              "objects": {},
              "orderBy": [
                {
                  "Direction": 1,
                  "Expression": {
                    "Column": {
                      "Expression": {
                        "SourceRef": {
                          "Entity": "public visits"
                        }
                      },
                      "Property": "Visit Hour"
                    }
                  }
                }
              ],
              "activeProjections": {
                "Category": [
                  {
                    "Column": {
                      "Expression": {
                        "SourceRef": {
                          "Entity": "public visits"
                        }
                      },
                      "Property": "Visit Hour"
                    }
                  }
                ]
              },
              "display": {
                "mode": "hidden"
              }
            }
          },
          "c9a9652dcebba9554bd6": {
            "filters": {
              "byExpr": [
                {
                  "name": "15a1e87d5737bb0ddcdd",
                  "type": "Advanced",
                  "expression": {
                    "Column": {
                      "Expression": {
                        "SourceRef": {
                          "Entity": "public visits"
                        }
                      },
                      "Property": "Visit Hour"
                    }
                  },
                  "howCreated": 0
                },
                {
                  "name": "6e8d4d40166a9259eca1",
                  "type": "Categorical",
                  "expression": {
                    "Column": {
                      "Expression": {
                        "SourceRef": {
                          "Entity": "public customers"
                        }
                      },
                      "Property": "Region"
                    }
                  },
                  "howCreated": 0
                },
                {
                  "name": "4174d03ac1481aed26a5",
                  "type": "Advanced",
                  "expression": {
                    "Aggregation": {
                      "Expression": {
                        "Column": {
                          "Expression": {
                            "SourceRef": {
                              "Entity": "public visits"
                            }
                          },
                          "Property": "Visit #"
                        }
                      },
                      "Function": 5
                    }
                  },
                  "howCreated": 0
                }
              ]
            },
            "singleVisual": {
              "visualType": "lineChart",
              "objects": {},
              "orderBy": [
                {
                  "Direction": 1,
                  "Expression": {
                    "Column": {
                      "Expression": {
                        "SourceRef": {
                          "Entity": "public visits"
                        }
                      },
                      "Property": "Visit Hour"
                    }
                  }
                }
              ],
              "activeProjections": {
                "Category": [
                  {
                    "Column": {
                      "Expression": {
                        "SourceRef": {
                          "Entity": "public visits"
                        }
                      },
                      "Property": "Visit Hour"
                    }
                  }
                ]
              }
            }
          },
          "127e874e9978b5317405": {
            "filters": {
              "byExpr": [
                {
                  "name": "a8f92e1a7321d2b20189",
                  "type": "Categorical",
                  "expression": {
                    "Column": {
                      "Expression": {
                        "SourceRef": {
                          "Entity": "public visits"
                        }
                      },
                      "Property": "Day Name"
                    }
                  },
                  "howCreated": 0
                },
                {
                  "name": "53549a109460eedc6804",
                  "type": "Categorical",
                  "expression": {
                    "Column": {
                      "Expression": {
                        "SourceRef": {
                          "Entity": "public customers"
                        }
                      },
                      "Property": "Region"
                    }
                  },
                  "howCreated": 0
                },
                {
                  "name": "b2232d0d6a52709637eb",
                  "type": "Advanced",
                  "expression": {
                    "Aggregation": {
                      "Expression": {
                        "Column": {
                          "Expression": {
                            "SourceRef": {
                              "Entity": "public visits"
                            }
                          },
                          "Property": "Visit #"
                        }
                      },
                      "Function": 5
                    }
                  },
                  "howCreated": 0
                }
              ]
            },
            "singleVisual": {
              "visualType": "lineChart",
              "objects": {},
              "activeProjections": {
                "Category": [
                  {
                    "Column": {
                      "Expression": {
                        "SourceRef": {
                          "Entity": "public visits"
                        }
                      },
                      "Property": "Day Name"
                    }
                  }
                ]
              }
            }
          },
          "4f874f7106243c9be0c1": {
            "filters": {
              "byExpr": [
                {
                  "name": "d6a78460d4525a210321",
                  "type": "Categorical",
                  "filter": {
                    "Version": 2,
                    "From": [
                      {
                        "Name": "p",
                        "Entity": "public business_units",
                        "Type": 0
                      }
                    ],
                    "Where": [
                      {
                        "Condition": {
                          "Not": {
                            "Expression": {
                              "In": {
                                "Expressions": [
                                  {
                                    "Column": {
                                      "Expression": {
                                        "SourceRef": {
                                          "Source": "p"
                                        }
                                      },
                                      "Property": "Business Unit"
                                    }
                                  }
                                ],
                                "Values": [
                                  [
                                    {
                                      "Literal": {
                                        "Value": "null"
                                      }
                                    }
                                  ],
                                  [
                                    {
                                      "Literal": {
                                        "Value": "'OTHERS'"
                                      }
                                    }
                                  ]
                                ]
                              }
                            }
                          }
                        }
                      }
                    ]
                  },
                  "expression": {
                    "Column": {
                      "Expression": {
                        "SourceRef": {
                          "Entity": "public business_units"
                        }
                      },
                      "Property": "Business Unit"
                    }
                  },
                  "howCreated": 1
                },
                {
                  "name": "df598f609c1350ca3b08",
                  "type": "Categorical",
                  "expression": {
                    "Column": {
                      "Expression": {
                        "SourceRef": {
                          "Entity": "public visits"
                        }
                      },
                      "Property": "Day Name"
                    }
                  },
                  "howCreated": 0
                },
                {
                  "name": "aefffad8524821a1c013",
                  "type": "Advanced",
                  "expression": {
                    "Aggregation": {
                      "Expression": {
                        "Column": {
                          "Expression": {
                            "SourceRef": {
                              "Entity": "public visits"
                            }
                          },
                          "Property": "Visit #"
                        }
                      },
                      "Function": 5
                    }
                  },
                  "howCreated": 0
                },
                {
                  "name": "f5f15e6dcce443134ca5",
                  "type": "Categorical",
                  "expression": {
                    "Column": {
                      "Expression": {
                        "SourceRef": {
                          "Entity": "public business_units"
                        }
                      },
                      "Property": "Business Unit Mask"
                    }
                  },
                  "howCreated": 0
                }
              ]
            },
            "singleVisual": {
              "visualType": "lineChart",
              "objects": {},
              "activeProjections": {
                "Category": [
                  {
                    "Column": {
                      "Expression": {
                        "SourceRef": {
                          "Entity": "public visits"
                        }
                      },
                      "Property": "Day Name"
                    }
                  }
                ]
              },
              "display": {
                "mode": "hidden"
              }
            }
          },
          "35064b3aaed540958de2": {
            "filters": {
              "byName": {
                "19586c3a53a51e20d343": {
                  "name": "19586c3a53a51e20d343",
                  "type": "RelativeDate",
                  "filter": {
                    "Version": 2,
                    "From": [
                      {
                        "Name": "p1",
                        "Entity": "public visits",
                        "Type": 0
                      }
                    ],
                    "Where": [
                      {
                        "Condition": {
                          "Comparison": {
                            "ComparisonKind": 0,
                            "Left": {
                              "Column": {
                                "Expression": {
                                  "SourceRef": {
                                    "Source": "p1"
                                  }
                                },
                                "Property": "Visit Date"
                              }
                            },
                            "Right": {
                              "DateSpan": {
                                "Expression": {
                                  "Now": {}
                                },
                                "TimeUnit": 0
                              }
                            }
                          }
                        }
                      }
                    ]
                  },
                  "expression": {
                    "Column": {
                      "Expression": {
                        "SourceRef": {
                          "Entity": "public visits"
                        }
                      },
                      "Property": "Visit Date"
                    }
                  },
                  "howCreated": 1
                }
              },
              "byExpr": [
                {
                  "name": "e9cef1aba00758460635",
                  "type": "Advanced",
                  "expression": {
                    "Aggregation": {
                      "Expression": {
                        "Column": {
                          "Expression": {
                            "SourceRef": {
                              "Entity": "public visits"
                            }
                          },
                          "Property": "Visit #"
                        }
                      },
                      "Function": 2
                    }
                  },
                  "howCreated": 0
                },
                {
                  "name": "0789928a1dd89202eb72",
                  "type": "Categorical",
                  "expression": {
                    "Column": {
                      "Expression": {
                        "SourceRef": {
                          "Entity": "public users"
                        }
                      },
                      "Property": "Frontline Mask"
                    }
                  },
                  "howCreated": 0
                }
              ]
            },
            "singleVisual": {
              "visualType": "pivotTable",
              "objects": {},
              "activeProjections": {
                "Columns": [
                  {
                    "Column": {
                      "Expression": {
                        "SourceRef": {
                          "Entity": "public visits"
                        }
                      },
                      "Property": "Visit Date"
                    }
                  }
                ],
                "Rows": [
                  {
                    "Column": {
                      "Expression": {
                        "SourceRef": {
                          "Entity": "public users"
                        }
                      },
                      "Property": "Frontline Mask"
                    }
                  }
                ]
              }
            }
          },
          "d92418f3d6ba070c09ac": {
            "filters": {
              "byExpr": [
                {
                  "name": "b446e9d04143e482c705",
                  "type": "Advanced",
                  "expression": {
                    "Column": {
                      "Expression": {
                        "SourceRef": {
                          "Entity": "public visits"
                        }
                      },
                      "Property": "Visit Hour"
                    }
                  },
                  "howCreated": 0
                },
                {
                  "name": "821850d34e0003a48041",
                  "type": "Categorical",
                  "expression": {
                    "Column": {
                      "Expression": {
                        "SourceRef": {
                          "Entity": "public visits"
                        }
                      },
                      "Property": "Day Name"
                    }
                  },
                  "howCreated": 0
                },
                {
                  "name": "c66d04704c0e7870b3b0",
                  "type": "Advanced",
                  "expression": {
                    "Aggregation": {
                      "Expression": {
                        "Column": {
                          "Expression": {
                            "SourceRef": {
                              "Entity": "public visits"
                            }
                          },
                          "Property": "Visit #"
                        }
                      },
                      "Function": 2
                    }
                  },
                  "howCreated": 0
                }
              ]
            },
            "singleVisual": {
              "visualType": "pivotTable",
              "objects": {},
              "orderBy": [
                {
                  "Direction": 1,
                  "Expression": {
                    "Column": {
                      "Expression": {
                        "SourceRef": {
                          "Entity": "public visits"
                        }
                      },
                      "Property": "Visit Hour"
                    }
                  }
                }
              ],
              "activeProjections": {
                "Columns": [
                  {
                    "Column": {
                      "Expression": {
                        "SourceRef": {
                          "Entity": "public visits"
                        }
                      },
                      "Property": "Visit Hour"
                    }
                  }
                ],
                "Rows": [
                  {
                    "Column": {
                      "Expression": {
                        "SourceRef": {
                          "Entity": "public visits"
                        }
                      },
                      "Property": "Day Name"
                    }
                  }
                ]
              }
            }
          },
          "8e6b56182aaa0ca17243": {
            "singleVisual": {
              "visualType": "actionButton",
              "objects": {}
            }
          },
          "ec98c2462757355e04da": {
            "singleVisual": {
              "visualType": "actionButton",
              "objects": {}
            }
          },
          "ec080d215cc6e0bd5b06": {
            "singleVisual": {
              "visualType": "shape",
              "objects": {}
            }
          },
          "59500c8451eeed88a37e": {
            "filters": {
              "byExpr": [
                {
                  "name": "28541ef0864300e14050",
                  "type": "Categorical",
                  "expression": {
                    "Column": {
                      "Expression": {
                        "SourceRef": {
                          "Entity": "public objectives"
                        }
                      },
                      "Property": "Objective Category"
                    }
                  },
                  "howCreated": 0
                },
                {
                  "name": "620886e403a4e08c0b0d",
                  "type": "Categorical",
                  "expression": {
                    "Column": {
                      "Expression": {
                        "SourceRef": {
                          "Entity": "public objectives"
                        }
                      },
                      "Property": "Objective"
                    }
                  },
                  "howCreated": 0
                }
              ]
            },
            "singleVisual": {
              "visualType": "slicer",
              "objects": {
                "merge": {
                  "data": [
                    {
                      "properties": {
                        "mode": {
                          "expr": {
                            "Literal": {
                              "Value": "'Basic'"
                            }
                          }
                        }
                      }
                    }
                  ]
                }
              },
              "activeProjections": {
                "Values": [
                  {
                    "Column": {
                      "Expression": {
                        "SourceRef": {
                          "Entity": "public objectives"
                        }
                      },
                      "Property": "Objective Category"
                    }
                  }
                ]
              },
              "expansionStates": [
                {
                  "roles": [
                    "Values"
                  ],
                  "levels": [
                    {
                      "queryRefs": [
                        "public objectives.category"
                      ],
                      "isCollapsed": true,
                      "identityKeys": [
                        {
                          "Column": {
                            "Expression": {
                              "SourceRef": {
                                "Entity": "public objectives"
                              }
                            },
                            "Property": "Objective Category"
                          }
                        }
                      ],
                      "isPinned": true
                    },
                    {
                      "queryRefs": [
                        "public objectives.name"
                      ],
                      "isCollapsed": true,
                      "isPinned": true
                    }
                  ],
                  "root": {
                    "identityValues": []
                  }
                }
              ]
            }
          },
          "01c2f3712d39b783bb77": {
            "filters": {
              "byExpr": [
                {
                  "name": "6137365b6bebb70b09b0",
                  "type": "Categorical",
                  "expression": {
                    "Column": {
                      "Expression": {
                        "SourceRef": {
                          "Entity": "public visits"
                        }
                      },
                      "Property": "Date Local"
                    }
                  },
                  "howCreated": 0
                }
              ]
            },
            "singleVisual": {
              "visualType": "slicer",
              "objects": {
                "merge": {
                  "data": [
                    {
                      "properties": {
                        "mode": {
                          "expr": {
                            "Literal": {
                              "Value": "'Between'"
                            }
                          }
                        }
                      }
                    }
                  ]
                }
              },
              "orderBy": [
                {
                  "Direction": 1,
                  "Expression": {
                    "Column": {
                      "Expression": {
                        "SourceRef": {
                          "Entity": "public visits"
                        }
                      },
                      "Property": "Date Local"
                    }
                  }
                }
              ],
              "activeProjections": {
                "Values": [
                  {
                    "Column": {
                      "Expression": {
                        "SourceRef": {
                          "Entity": "public visits"
                        }
                      },
                      "Property": "Date Local"
                    }
                  }
                ]
              }
            }
          },
          "9a8f590f15430c64442c": {
            "singleVisual": {
              "visualType": "textbox",
              "objects": {}
            }
          },
          "b5defe4ce068844ad106": {
            "filters": {
              "byExpr": [
                {
                  "name": "4e67190664d629e2d200",
                  "type": "Categorical",
                  "expression": {
                    "Column": {
                      "Expression": {
                        "SourceRef": {
                          "Entity": "public visits"
                        }
                      },
                      "Property": "Visit #"
                    }
                  },
                  "howCreated": 0
                }
              ]
            },
            "singleVisual": {
              "visualType": "slicer",
              "objects": {
                "merge": {
                  "data": [
                    {
                      "properties": {
                        "mode": {
                          "expr": {
                            "Literal": {
                              "Value": "'Dropdown'"
                            }
                          }
                        }
                      }
                    }
                  ]
                }
              },
              "activeProjections": {
                "Values": [
                  {
                    "Column": {
                      "Expression": {
                        "SourceRef": {
                          "Entity": "public visits"
                        }
                      },
                      "Property": "Visit #"
                    }
                  }
                ]
              }
            }
          },
          "95895f54a692e600d350": {
            "filters": {
              "byExpr": [
                {
                  "name": "73c6273d9dbd2bad505e",
                  "type": "Categorical",
                  "expression": {
                    "Column": {
                      "Expression": {
                        "SourceRef": {
                          "Entity": "public business_units"
                        }
                      },
                      "Property": "Business Unit Mask"
                    }
                  },
                  "howCreated": 0
                },
                {
                  "name": "f78146d4d79169eb66c0",
                  "type": "Categorical",
                  "expression": {
                    "Column": {
                      "Expression": {
                        "SourceRef": {
                          "Entity": "public business_lines"
                        }
                      },
                      "Property": "Product Category"
                    }
                  },
                  "howCreated": 0
                },
                {
                  "name": "3bed825355203e395012",
                  "type": "Categorical",
                  "expression": {
                    "Column": {
                      "Expression": {
                        "SourceRef": {
                          "Entity": "public business_lines"
                        }
                      },
                      "Property": "Business Line Mask"
                    }
                  },
                  "howCreated": 0
                }
              ]
            },
            "singleVisual": {
              "visualType": "slicer",
              "objects": {
                "merge": {
                  "data": [
                    {
                      "properties": {
                        "mode": {
                          "expr": {
                            "Literal": {
                              "Value": "'Basic'"
                            }
                          }
                        }
                      }
                    }
                  ]
                }
              },
              "activeProjections": {
                "Values": [
                  {
                    "Column": {
                      "Expression": {
                        "SourceRef": {
                          "Entity": "public business_units"
                        }
                      },
                      "Property": "Business Unit Mask"
                    }
                  }
                ]
              },
              "expansionStates": [
                {
                  "roles": [
                    "Values"
                  ],
                  "levels": [
                    {
                      "queryRefs": [
                        "public business_units.Business Unit Mask"
                      ],
                      "isCollapsed": true,
                      "identityKeys": [
                        {
                          "Column": {
                            "Expression": {
                              "SourceRef": {
                                "Entity": "public business_units"
                              }
                            },
                            "Property": "Business Unit Mask"
                          }
                        }
                      ],
                      "isPinned": true
                    },
                    {
                      "queryRefs": [
                        "public business_lines.category"
                      ],
                      "isCollapsed": true,
                      "identityKeys": [
                        {
                          "Column": {
                            "Expression": {
                              "SourceRef": {
                                "Entity": "public business_lines"
                              }
                            },
                            "Property": "Product Category"
                          }
                        }
                      ],
                      "isPinned": true
                    },
                    {
                      "queryRefs": [
                        "public business_lines.Business Line Mask"
                      ],
                      "isCollapsed": true,
                      "isPinned": true
                    }
                  ],
                  "root": {
                    "identityValues": []
                  }
                }
              ]
            }
          },
          "554423c0be108863eba1": {
            "singleVisual": {
              "visualType": "actionButton",
              "objects": {}
            }
          },
          "346b79f147d6e6015bd1": {
            "filters": {
              "byExpr": [
                {
                  "name": "adf0bb925ed0e284361d",
                  "type": "Advanced",
                  "filter": {
                    "Version": 2,
                    "From": [
                      {
                        "Name": "p",
                        "Entity": "public customers",
                        "Type": 0
                      }
                    ],
                    "Where": [
                      {
                        "Condition": {
                          "Not": {
                            "Expression": {
                              "Comparison": {
                                "ComparisonKind": 0,
                                "Left": {
                                  "Column": {
                                    "Expression": {
                                      "SourceRef": {
                                        "Source": "p"
                                      }
                                    },
                                    "Property": "Region"
                                  }
                                },
                                "Right": {
                                  "Literal": {
                                    "Value": "null"
                                  }
                                }
                              }
                            }
                          }
                        }
                      }
                    ]
                  },
                  "expression": {
                    "Column": {
                      "Expression": {
                        "SourceRef": {
                          "Entity": "public customers"
                        }
                      },
                      "Property": "Region"
                    }
                  },
                  "howCreated": 1
                },
                {
                  "name": "487cfb2a8928c5bbf456",
                  "type": "Categorical",
                  "filter": {
                    "Version": 2,
                    "From": [
                      {
                        "Name": "p",
                        "Entity": "public visits",
                        "Type": 0
                      }
                    ],
                    "Where": [
                      {
                        "Condition": {
                          "Not": {
                            "Expression": {
                              "In": {
                                "Expressions": [
                                  {
                                    "Column": {
                                      "Expression": {
                                        "SourceRef": {
                                          "Source": "p"
                                        }
                                      },
                                      "Property": "AfterHours_Home_OR"
                                    }
                                  }
                                ],
                                "Values": [
                                  [
                                    {
                                      "Literal": {
                                        "Value": "null"
                                      }
                                    }
                                  ]
                                ]
                              }
                            }
                          }
                        }
                      }
                    ]
                  },
                  "expression": {
                    "Column": {
                      "Expression": {
                        "SourceRef": {
                          "Entity": "public visits"
                        }
                      },
                      "Property": "AfterHours_Home_OR"
                    }
                  },
                  "howCreated": 0
                }
              ]
            },
            "singleVisual": {
              "visualType": "slicer",
              "objects": {
                "merge": {
                  "data": [
                    {
                      "properties": {
                        "mode": {
                          "expr": {
                            "Literal": {
                              "Value": "'Basic'"
                            }
                          }
                        }
                      }
                    }
                  ]
                }
              },
              "activeProjections": {
                "Values": [
                  {
                    "Column": {
                      "Expression": {
                        "SourceRef": {
                          "Entity": "public visits"
                        }
                      },
                      "Property": "AfterHours_Home_OR"
                    }
                  }
                ]
              }
            }
          },
          "ac5d04e864192bb00150": {
            "filters": {
              "byExpr": [
                {
                  "name": "be7e0c50606096ca45a0",
                  "type": "Categorical",
                  "expression": {
                    "Column": {
                      "Expression": {
                        "SourceRef": {
                          "Entity": "public users"
                        }
                      },
                      "Property": "Frontline Mask"
                    }
                  },
                  "howCreated": 0
                }
              ]
            },
            "singleVisual": {
              "visualType": "slicer",
              "objects": {
                "merge": {
                  "data": [
                    {
                      "properties": {
                        "mode": {
                          "expr": {
                            "Literal": {
                              "Value": "'Dropdown'"
                            }
                          }
                        }
                      }
                    }
                  ]
                }
              },
              "activeProjections": {
                "Values": [
                  {
                    "Column": {
                      "Expression": {
                        "SourceRef": {
                          "Entity": "public users"
                        }
                      },
                      "Property": "Frontline Mask"
                    }
                  }
                ]
              }
            }
          },
          "0416dc2514d1a1c3e2d8": {
            "singleVisual": {
              "visualType": "actionButton",
              "objects": {}
            }
          },
          "8eadd82d15bb835c2a5d": {
            "filters": {
              "byExpr": [
                {
                  "name": "adf0bb925ed0e284361d",
                  "type": "Advanced",
                  "filter": {
                    "Version": 2,
                    "From": [
                      {
                        "Name": "p",
                        "Entity": "public customers",
                        "Type": 0
                      }
                    ],
                    "Where": [
                      {
                        "Condition": {
                          "Not": {
                            "Expression": {
                              "Comparison": {
                                "ComparisonKind": 0,
                                "Left": {
                                  "Column": {
                                    "Expression": {
                                      "SourceRef": {
                                        "Source": "p"
                                      }
                                    },
                                    "Property": "Region"
                                  }
                                },
                                "Right": {
                                  "Literal": {
                                    "Value": "null"
                                  }
                                }
                              }
                            }
                          }
                        }
                      }
                    ]
                  },
                  "expression": {
                    "Column": {
                      "Expression": {
                        "SourceRef": {
                          "Entity": "public customers"
                        }
                      },
                      "Property": "Region"
                    }
                  },
                  "howCreated": 0
                },
                {
                  "name": "d735e10ad58cc4279910",
                  "type": "Categorical",
                  "expression": {
                    "Column": {
                      "Expression": {
                        "SourceRef": {
                          "Entity": "public customers"
                        }
                      },
                      "Property": "City"
                    }
                  },
                  "howCreated": 0
                },
                {
                  "name": "337935742332cbca36ca",
                  "type": "Categorical",
                  "expression": {
                    "Column": {
                      "Expression": {
                        "SourceRef": {
                          "Entity": "public customers"
                        }
                      },
                      "Property": "Sector"
                    }
                  },
                  "howCreated": 0
                },
                {
                  "name": "36799d8de3a9a176e25d",
                  "type": "Categorical",
                  "expression": {
                    "Column": {
                      "Expression": {
                        "SourceRef": {
                          "Entity": "public customers"
                        }
                      },
                      "Property": "Customer Name Mask"
                    }
                  },
                  "howCreated": 0
                }
              ]
            },
            "singleVisual": {
              "visualType": "slicer",
              "objects": {
                "merge": {
                  "data": [
                    {
                      "properties": {
                        "mode": {
                          "expr": {
                            "Literal": {
                              "Value": "'Basic'"
                            }
                          }
                        }
                      }
                    }
                  ]
                }
              },
              "activeProjections": {
                "Values": [
                  {
                    "Column": {
                      "Expression": {
                        "SourceRef": {
                          "Entity": "public customers"
                        }
                      },
                      "Property": "Region"
                    }
                  }
                ]
              },
              "expansionStates": [
                {
                  "roles": [
                    "Values"
                  ],
                  "levels": [
                    {
                      "queryRefs": [
                        "public customers.region"
                      ],
                      "isCollapsed": true,
                      "identityKeys": [
                        {
                          "Column": {
                            "Expression": {
                              "SourceRef": {
                                "Entity": "public customers"
                              }
                            },
                            "Property": "Region"
                          }
                        }
                      ],
                      "isPinned": true
                    },
                    {
                      "queryRefs": [
                        "public customers.city"
                      ],
                      "isCollapsed": true,
                      "identityKeys": [
                        {
                          "Column": {
                            "Expression": {
                              "SourceRef": {
                                "Entity": "public customers"
                              }
                            },
                            "Property": "City"
                          }
                        }
                      ],
                      "isPinned": true
                    },
                    {
                      "queryRefs": [
                        "public customers.sector"
                      ],
                      "isCollapsed": true,
                      "identityKeys": [
                        {
                          "Column": {
                            "Expression": {
                              "SourceRef": {
                                "Entity": "public customers"
                              }
                            },
                            "Property": "Sector"
                          }
                        }
                      ],
                      "isPinned": true
                    },
                    {
                      "queryRefs": [
                        "public customers.Customer Name Mask"
                      ],
                      "isCollapsed": true,
                      "isPinned": true
                    }
                  ],
                  "root": {
                    "identityValues": [],
                    "children": [
                      {
                        "identityValues": [
                          {
                            "Literal": {
                              "Value": "null"
                            }
                          }
                        ],
                        "children": [
                          {
                            "identityValues": [
                              {
                                "Literal": {
                                  "Value": "null"
                                }
                              }
                            ],
                            "isToggled": true
                          }
                        ]
                      }
                    ]
                  }
                }
              ]
            }
          }
        },
        "visualContainerGroups": {
          "469ab4e5bbc2c210b89b": {
            "isHidden": true
          }
        }
      }
    },
    "objects": {
      "merge": {
        "outspacePane": [
          {
            "properties": {
              "expanded": {
                "expr": {
                  "Literal": {
                    "Value": "false"
                  }
                }
              },
              "visible": {
                "expr": {
                  "Literal": {
                    "Value": "false"
                  }
                }
              }
            }
          }
        ]
      }
    }
  }
}